{
  "current_node": "node_a",
  "previous_node": "node_c",
  "status": "ready_for_node_a",
  "latest_run_dir": "runs/20260421_084530_bf16_gemm_v1_81595f4",
  "latest_summary_json": "state/latest_run.json",
  "latest_ncu_summary_json": "state/latest_ncu_summary.json",
  "latest_commit": "81595f4d260c48977738ee09ac229be6b457c789",
  "approved_direction_id": null,
  "recommended_direction_id": "dir_01",
  "current_kernel_path": "src/kernels/bf16_gemm_v1.cu",
  "plateau_counter": 62,
  "notes": "Node C build succeeded for round 75/100. Node A will now measure the new code path."
}
