{
  "current_node": "node_a",
  "previous_node": "node_c",
  "status": "ready_for_node_a",
  "latest_run_dir": "runs/20260421_084358_bf16_gemm_v1_d912e68",
  "latest_summary_json": "state/latest_run.json",
  "latest_ncu_summary_json": "state/latest_ncu_summary.json",
  "latest_commit": "d912e6859ddbfa1897a16f5deecdbcc4060a1c95",
  "approved_direction_id": null,
  "recommended_direction_id": "dir_01",
  "current_kernel_path": "src/kernels/bf16_gemm_v1.cu",
  "plateau_counter": 53,
  "notes": "Node C build succeeded for round 66/100. Node A will now measure the new code path."
}
