{
  "current_node": "node_b",
  "previous_node": "node_a",
  "status": "ready_for_node_b",
  "latest_run_dir": "runs/20260421_084553_bf16_gemm_v1_9b3911b",
  "latest_summary_json": "state/latest_run.json",
  "latest_ncu_summary_json": "state/latest_ncu_summary.json",
  "latest_commit": "9b3911b9112b72e2a0cb78ff6dcebd190210ed41",
  "approved_direction_id": null,
  "recommended_direction_id": null,
  "current_kernel_path": "src/kernels/bf16_gemm_v1.cu",
  "plateau_counter": 64,
  "notes": "Node A completed round 76/100. Run node_b to continue round 77/100."
}
