{
  "current_node": "node_b",
  "previous_node": "node_a",
  "status": "ready_for_node_b",
  "latest_run_dir": "runs/20260421_183233_bf16_gemm_v1_4948b8ea",
  "latest_summary_json": "state/latest_run.json",
  "latest_ncu_summary_json": "state/latest_ncu_summary.json",
  "latest_commit": "4948b8ea197c9869356471fedefa11a45b84ee35",
  "approved_direction_id": null,
  "recommended_direction_id": null,
  "current_kernel_path": "src/kernels/bf16_gemm_v1.cu",
  "plateau_counter": 21,
  "notes": "Node A completed round 4/20. Run node_b to continue round 5/20."
}
