{
  "current_node": "node_b",
  "previous_node": "node_a",
  "status": "ready_for_node_b",
  "latest_run_dir": "runs/20260421_003431_bf16_gemm_v1_f198bbb",
  "latest_summary_json": "state/latest_run.json",
  "latest_ncu_summary_json": "state/latest_ncu_summary.json",
  "latest_commit": "f198bbbac12d7c8ca3363403eb929e2abfb04b43",
  "approved_direction_id": null,
  "recommended_direction_id": null,
  "current_kernel_path": "src/kernels/bf16_gemm_v1.cu",
  "plateau_counter": 7,
  "notes": "Node A completed round 19/100. Run node_b to continue round 20/100."
}
