{
  "schema_version": 1,
  "attempt_id": "diagnosis_20260421_012002:dir_01",
  "status": "measured",
  "candidate_id": "diagnosis_20260421_012002:dir_01",
  "source_diagnosis_id": "diagnosis_20260421_012002",
  "base_run_id": "20260421_011816_bf16_gemm_v1_20cad79",
  "family_id": "legacy::restore_accepted_grouped_rows_8_hot_band_consumer_ordering",
  "subfamily_id": "legacy::restore_accepted_grouped_rows_8_hot_band_consumer_ordering",
  "direction_id": "dir_01",
  "direction_name": "Restore Accepted Grouped-Rows-8 Hot-Band Consumer Ordering",
  "mode": "restore",
  "commit": "803e7499227b26770fccecb4b6d03f4079a5f06c",
  "commit_short": "803e749",
  "subject": "node_c: round 28/100 implement dir_01 Restore Accepted Grouped-Rows-8 Hot-Band Consumer Ordering",
  "selection_mode": "recommended",
  "selected_at": "2026-04-21T01:21:09-07:00",
  "selected_from_frontier_id": "frontier:global",
  "source_run_id": "20260421_011816_bf16_gemm_v1_20cad79",
  "selection_score": 2.265,
  "planned_action_fingerprint": "restore_grouped_rows_8_ptx_consumer_ordering_surface",
  "implemented_action_fingerprint": "restore_grouped_rows_8_ptx_consumer_ordering_surface",
  "score_breakdown": {
    "policy_id": "manual_round100_node_b_v28",
    "rank_score": 1.32,
    "surface_diversity_bonus": 0.28,
    "queue_resolution_bonus": 0.32,
    "user_guidance_bonus": 0.16,
    "fresh_anchor_bonus": 0.22,
    "risk_penalty": 0.12,
    "formula": "rank_score + surface_diversity_bonus + queue_resolution_bonus + user_guidance_bonus + fresh_anchor_bonus - risk_penalty"
  },
  "semantic_delta_tags": [
    "single_direction_attempt",
    "kernel_code"
  ],
  "secondary_family_ids": [],
  "actual_code_regions": [
    "src/kernels/bf16_gemm_v1.cu"
  ],
  "implementation": {
    "commit": "803e7499227b26770fccecb4b6d03f4079a5f06c",
    "commit_short": "803e749",
    "subject": "node_c: round 28/100 implement dir_01 Restore Accepted Grouped-Rows-8 Hot-Band Consumer Ordering",
    "build_status": "PASS",
    "failure_mode": null,
    "build_log_path": "state/node_c_last_build.log",
    "touched_files": [
      "src/kernels/bf16_gemm_v1.cu"
    ],
    "diff_stats": {
      "files_changed": 1,
      "insertions": 1,
      "deletions": 1
    }
  },
  "build_status": "PASS",
  "failure_mode": null,
  "diff_stats": {
    "files_changed": 1,
    "insertions": 1,
    "deletions": 1
  },
  "measurement": {
    "run_id": "20260421_012143_bf16_gemm_v1_803e749",
    "measurement_commit": "803e7499227b26770fccecb4b6d03f4079a5f06c",
    "runtime_ms": 24.51711941,
    "runtime_delta_ms": 0.3496961600000006,
    "tflops": 29.65354166,
    "correctness": true,
    "headline_metrics": {
      "sm__pipe_tensor_cycles_active.avg.pct_of_peak_sustained_active": "48.30",
      "sm__throughput.avg.pct_of_peak_sustained_elapsed": "47.83",
      "gpu__compute_memory_throughput.avg.pct_of_peak_sustained_elapsed": "46.12",
      "dram__throughput.avg.pct_of_peak_sustained_elapsed": "9.77",
      "lts__throughput.avg.pct_of_peak_sustained_elapsed": "31.16",
      "sm__warps_active.avg.pct_of_peak_sustained_active": "16.59",
      "smsp__warp_issue_stalled_barrier_per_warp_active.pct": "5.19",
      "smsp__warp_issue_stalled_long_scoreboard_per_warp_active.pct": "7.34",
      "smsp__warp_issue_stalled_short_scoreboard_per_warp_active.pct": "2.17",
      "smsp__warp_issue_stalled_mio_throttle_per_warp_active.pct": "3.71",
      "launch__occupancy_limit_registers": "2"
    },
    "headline_metric_deltas_vs_previous_run": {}
  },
  "transition_class": "regressed",
  "close_reason": "measured_by_node_a",
  "notes": "Node A measured 20260421_012143_bf16_gemm_v1_803e749 for candidate diagnosis_20260421_012002:dir_01; transition_label=PASS_LOSS.",
  "transition_label": "PASS_LOSS"
}
