{
  "run_id": "20260420_092926_bf16_gemm_v1_8c2a778",
  "run_dir": "runs/20260420_092926_bf16_gemm_v1_8c2a778",
  "raw_summary_json": "runs/20260420_092926_bf16_gemm_v1_8c2a778/summary.json",
  "raw_summary_md": "runs/20260420_092926_bf16_gemm_v1_8c2a778/summary.md",
  "kernel_tag": "bf16_gemm_v1_8c2a778",
  "runner": "/home/aice/Desktop/matmul_optimizer/build/custom_runner",
  "dataset_id": "fixed_bf16_gemm_v1",
  "benchmark_case": "case_00_seed_3407",
  "correctness_passed": true,
  "correctness_cases_total": 3,
  "correctness_cases_passed": 3,
  "perf_passed": true,
  "median_runtime_ms": 25.69215965,
  "p10_runtime_ms": 25.20340519,
  "p90_runtime_ms": 26.25884171,
  "tflops": 28.29732617,
  "ncu_rep_path": "runs/20260420_092926_bf16_gemm_v1_8c2a778/ncu_profile.ncu-rep",
  "ncu_csv_path": "runs/20260420_092926_bf16_gemm_v1_8c2a778/ncu_metrics.csv",
  "ncu_summary_json": "state/latest_ncu_summary.json",
  "is_new_best_custom": false,
  "measured_commit": "8c2a778a7ff52bec9a777c667ae4be6ac96ce39f",
  "generated_at": "2026-04-20T09:29:33-07:00",
  "previous_run_id": "20260420_091644_bf16_gemm_v1_96154e3",
  "previous_median_runtime_ms": 25.56057644,
  "runtime_delta_ms": 0.13158321000000228,
  "tflops_delta": -0.14567171999999928,
  "perf_verdict": "regressed",
  "implemented_direction_id": "dir_01",
  "implemented_direction_name": "Restore grouped_rows=8, then align PTX export order with the reversed compute row-pair traversal",
  "implemented_selection_mode": "recommended",
  "implemented_idea_origin": "auto-analysis",
  "round_label": "round 65/100"
}
