{
  "run_id": "20260419_200457_bf16_gemm_v1_76622e3",
  "run_dir": "runs/20260419_200457_bf16_gemm_v1_76622e3",
  "raw_summary_json": "runs/20260419_200457_bf16_gemm_v1_76622e3/summary.json",
  "raw_summary_md": "runs/20260419_200457_bf16_gemm_v1_76622e3/summary.md",
  "kernel_tag": "bf16_gemm_v1_76622e3",
  "runner": "/home/aice/Desktop/matmul_optimizer/build/custom_runner",
  "dataset_id": "fixed_bf16_gemm_v1",
  "benchmark_case": "case_00_seed_3407",
  "correctness_passed": false,
  "correctness_cases_total": 3,
  "correctness_cases_passed": 0,
  "perf_passed": true,
  "median_runtime_ms": 31.33798409,
  "p10_runtime_ms": 30.75215416,
  "p90_runtime_ms": 31.9521801,
  "tflops": 23.19930407,
  "ncu_rep_path": "runs/20260419_200457_bf16_gemm_v1_76622e3/ncu_profile.ncu-rep",
  "ncu_csv_path": "runs/20260419_200457_bf16_gemm_v1_76622e3/ncu_metrics.csv",
  "ncu_summary_json": "state/latest_ncu_summary.json",
  "is_new_best_custom": false,
  "measured_commit": "76622e3953ae33585df08f275e54bdd27fad9860",
  "generated_at": "2026-04-19T20:05:04-07:00",
  "previous_run_id": "20260419_195339_bf16_gemm_v1_778a0b4",
  "previous_median_runtime_ms": 30.23612785,
  "runtime_delta_ms": 1.10185624,
  "tflops_delta": -0.8454223299999981,
  "perf_verdict": "regressed",
  "implemented_direction_id": "dir_01",
  "implemented_direction_name": "Human idea 7 Register reuse: keep the half-panel family and close the remaining correctness gap by single-sourcing warp ownership end to end",
  "implemented_selection_mode": "recommended",
  "implemented_idea_origin": "auto-analysis",
  "round_label": "round 19/20"
}
