{
  "active": true,
  "status": "awaiting_measurement",
  "total_rounds": 20,
  "completed_rounds": 15,
  "remaining_rounds": 5,
  "next_round_index": 16,
  "current_round_index": 16,
  "auto_use_recommended": true,
  "started_at": "2026-04-18T22:03:53-07:00",
  "completed_at": null,
  "last_completed_round": {
    "recorded_at": "2026-04-19T00:52:19-07:00",
    "round_index": 15,
    "total_rounds": 20,
    "direction_id": "dir_02",
    "direction_name": "Retile CTA and warp partition to trim per-warp N baggage",
    "selection_mode": "approved",
    "idea_origin": "auto-analysis",
    "hypothesis": "The current 4x2 warp layout with a wide per-warp N fanout keeps the accepted main/tail split, but each warp still carries multiple N fragments and a relatively heavy B-side footprint. Retiling the CTA or warp work split to reduce per-warp N baggage should ease fragment handling and MIO pressure without abandoning the proven split between the 64x128 main path and the 64x96 tail path.",
    "previous_run_id": "20260419_003937_bf16_gemm_v1_6eaca8e",
    "run_id": "20260419_005208_bf16_gemm_v1_8fbd2e5",
    "run_dir": "runs/20260419_005208_bf16_gemm_v1_8fbd2e5",
    "median_runtime_ms": 58.20516777,
    "runtime_delta_ms": 14.435743330000001,
    "tflops": 12.49063356,
    "tflops_delta": -4.119578499999999,
    "perf_verdict": "regressed",
    "correctness_passed": true,
    "measured_commit": "8fbd2e568cc6f3da25601cbfbf3ef2b64e8bf179",
    "ncu_summary_json": "state/latest_ncu_summary.json",
    "ncu_rep_path": "runs/20260419_005208_bf16_gemm_v1_8fbd2e5/ncu_profile.ncu-rep"
  },
  "accepted_base_run_id": "20260418_235548_bf16_gemm_v1_01d0040",
  "accepted_base_measured_commit": "01d00409efc03fdf555fef3ea7cc4efd403a720a",
  "accepted_base_runtime_ms": 43.69766426,
  "history_path": "state/round_history.jsonl",
  "notes": "Build passed for round 16/20. Node A will measure the result next."
}
