{
  "active": true,
  "status": "round_in_progress",
  "total_rounds": 100,
  "completed_rounds": 48,
  "remaining_rounds": 52,
  "next_round_index": 49,
  "current_round_index": 49,
  "auto_use_recommended": true,
  "auto_select_frontier": false,
  "started_at": "2026-04-20T21:51:52-07:00",
  "completed_at": null,
  "last_completed_round": {
    "recorded_at": "2026-04-21T08:39:37-07:00",
    "round_index": 48,
    "total_rounds": 100,
    "direction_id": "dir_01",
    "direction_name": "Restore The Best Measured PTX Grouping Window On The Accepted Surface",
    "selection_mode": "recommended",
    "idea_origin": "auto-analysis",
    "hypothesis": "The latest measured run landed at 24.440320 ms, still +0.276048 ms away from the accepted 24.164272 ms anchor. The fastest way to keep the loop grounded is to replay the exact accepted PTX surface before reopening another branch.",
    "previous_run_id": "20260421_083922_bf16_gemm_v1_cf4c90d",
    "run_id": "20260421_083931_bf16_gemm_v1_1161ff1",
    "run_dir": "runs/20260421_083931_bf16_gemm_v1_1161ff1",
    "median_runtime_ms": 24.42393589,
    "runtime_delta_ms": -0.016384120000001445,
    "tflops": 29.76667745,
    "tflops_delta": 0.019954769999998234,
    "perf_verdict": "improved",
    "correctness_passed": true,
    "measured_commit": "1161ff1fb47890c9c90710d70ca070db755a4548",
    "ncu_summary_json": "state/latest_ncu_summary.json",
    "ncu_rep_path": "runs/20260421_083931_bf16_gemm_v1_1161ff1/ncu_profile.ncu-rep"
  },
  "accepted_base_run_id": "20260420_235922_bf16_gemm_v1_489574e",
  "accepted_base_measured_commit": "489574ed5013268dbb79c634450d9a60155a294a",
  "accepted_base_runtime_ms": 24.16427231,
  "history_path": "state/round_history.jsonl",
  "notes": "Executing round 49/100."
}
