{
  "active": true,
  "status": "awaiting_measurement",
  "total_rounds": 100,
  "completed_rounds": 87,
  "remaining_rounds": 13,
  "next_round_index": 88,
  "current_round_index": 88,
  "auto_use_recommended": true,
  "auto_select_frontier": false,
  "started_at": "2026-04-20T21:51:52-07:00",
  "completed_at": null,
  "last_completed_round": {
    "recorded_at": "2026-04-21T08:47:49-07:00",
    "round_index": 87,
    "total_rounds": 100,
    "direction_id": "dir_01",
    "direction_name": "Continue The Active PTX One-K 128x128 Control-Path Exploit",
    "selection_mode": "recommended",
    "idea_origin": "auto-analysis",
    "hypothesis": "The latest run is 24.506880 ms against an accepted anchor of 24.164272 ms. Round round 86/100 should replay the bounded `control_path` family once from the current state so the search keeps advancing instead of restoring forever.",
    "previous_run_id": "20260421_084733_bf16_gemm_v1_1bd7b32",
    "run_id": "20260421_084743_bf16_gemm_v1_980ec98",
    "run_dir": "runs/20260421_084743_bf16_gemm_v1_980ec98",
    "median_runtime_ms": 24.63948822,
    "runtime_delta_ms": 0.13260840999999957,
    "tflops": 29.5062712,
    "tflops_delta": -0.1596604699999986,
    "perf_verdict": "regressed",
    "correctness_passed": true,
    "measured_commit": "980ec9821870411c14894bdebf30b8aca9d97a21",
    "ncu_summary_json": "state/latest_ncu_summary.json",
    "ncu_rep_path": "runs/20260421_084743_bf16_gemm_v1_980ec98/ncu_profile.ncu-rep"
  },
  "accepted_base_run_id": "20260420_235922_bf16_gemm_v1_489574e",
  "accepted_base_measured_commit": "489574ed5013268dbb79c634450d9a60155a294a",
  "accepted_base_runtime_ms": 24.16427231,
  "history_path": "state/round_history.jsonl",
  "notes": "Build passed for round 88/100. Node A will measure the result next."
}
