{
  "schema_version": 1,
  "candidate_set_id": "candidate_set:diagnosis_20260421_150626_round01_clean_6cc462c4",
  "source_run_id": "20260421_150626_bf16_gemm_v1_6cc462c4",
  "source_diagnosis_id": "diagnosis_20260421_150626_round01_clean_6cc462c4",
  "generated_at": "2026-04-21T15:08:54-07:00",
  "recommended_direction_id": "dir_01",
  "recommended_candidate_id": "diagnosis_20260421_150626_round01_clean_6cc462c4:dir_01",
  "candidates": [
    {
      "candidate_id": "diagnosis_20260421_150626_round01_clean_6cc462c4:dir_01",
      "source_diagnosis_id": "diagnosis_20260421_150626_round01_clean_6cc462c4",
      "base_run_id": "20260421_150626_bf16_gemm_v1_6cc462c4",
      "base_measured_commit": "6cc462c46b05712b972773911a1a7f31892ddcb2",
      "base_runtime_ms": 24.32352066,
      "direction_id": "dir_01",
      "direction_name": "Increase PTX Grouped-Row Depth On The Clean Baseline",
      "family_id": "launch_order::ptx_hotband_grouped_rows_tune",
      "subfamily_id": "launch_order::grouped_rows_4_to_8_for_b_reuse",
      "action_fingerprint": "clean_ptx_hotband_baseline:grouped_rows_4->8",
      "rank_in_diagnosis": 1,
      "recommended": true,
      "mode": "exploit",
      "priority": 0.79,
      "search_score_v1": 0.79,
      "score_breakdown": {
        "expected_gain": 0.27,
        "implementation_risk": 0.15,
        "evidence_strength": 0.16,
        "code_reuse": 0.21
      },
      "predicted_gain_ms": 0.7,
      "predicted_fail_risk": 0.24,
      "ranking_notes": [
        "This is the fastest clean experiment to run on the accepted PTX hot-band baseline.",
        "It keeps the search on the same family that currently produces the best custom runtime."
      ],
      "hypothesis": "The accepted PTX hot-band baseline may still be wasting issue slots because each hot-band B tile is only reused across four adjacent row tiles before the traversal advances columns. Increasing kFixedHotBandPtxGroupedRows from 4 to 8 should keep each B tile live across more rows, potentially reducing scoreboard pressure without changing the row split or K-stage structure.",
      "expected_bottleneck": "launch-order and B-tile reuse inefficiency inside the accepted PTX hot-band traversal",
      "code_locations": [
        "src/kernels/bf16_gemm_v1.cu:156",
        "src/kernels/bf16_gemm_v1.cu:1983",
        "src/kernels/bf16_gemm_v1.cu:1988",
        "src/kernels/bf16_gemm_v1.cu:2114"
      ],
      "risk": "Low-to-moderate risk: the edit is isolated, but deeper row grouping can help B reuse while hurting A locality or cache balance.",
      "metrics_to_recheck": [
        "median runtime",
        "smsp__warp_issue_stalled_long_scoreboard_per_warp_active.pct",
        "lts__throughput.avg.pct_of_peak_sustained_elapsed",
        "smsp__warp_issue_stalled_barrier_per_warp_active.pct"
      ],
      "stop_condition": "Stop if runtime change stays within noise or if long-scoreboard stalls rise after the first clean measurement.",
      "evidence_refs": [
        "runs/20260421_150626_bf16_gemm_v1_6cc462c4/ncu_analysis.md",
        "runs/20260421_150524_cublas_ref_clean_post_cleanup/ncu_analysis.md",
        "src/kernels/bf16_gemm_v1.cu"
      ],
      "target_hotspots": [
        {
          "scope_type": "section",
          "scope_name": "GPU Speed Of Light Throughput",
          "location": "GPU Speed Of Light Throughput"
        }
      ],
      "expected_local_changes": [
        "Keep the accepted PTX hot-band row split and default launch intact.",
        "Increase kFixedHotBandPtxGroupedRows from 4 to 8 and remeasure on the same fixed benchmark."
      ],
      "guardrail_metrics": [
        {
          "metric_name": "smsp__warp_issue_stalled_long_scoreboard_per_warp_active.pct",
          "guardrail": "non_increasing"
        },
        {
          "metric_name": "lts__throughput.avg.pct_of_peak_sustained_elapsed",
          "guardrail": "non_decreasing"
        }
      ],
      "status": "open"
    },
    {
      "candidate_id": "diagnosis_20260421_150626_round01_clean_6cc462c4:dir_02",
      "source_diagnosis_id": "diagnosis_20260421_150626_round01_clean_6cc462c4",
      "base_run_id": "20260421_150626_bf16_gemm_v1_6cc462c4",
      "base_measured_commit": "6cc462c46b05712b972773911a1a7f31892ddcb2",
      "base_runtime_ms": 24.32352066,
      "direction_id": "dir_02",
      "direction_name": "Swap To The Single-K 128x128 Non-Microkernel Sibling",
      "family_id": "kernel_variant::swap_to_nonmicrokernel_128x128",
      "subfamily_id": "kernel_variant::fixed_hot_band_128x128_regular_accumulate",
      "action_fingerprint": "clean_ptx_hotband_baseline:microkernel->regular_128x128_single_k",
      "rank_in_diagnosis": 2,
      "recommended": false,
      "mode": "exploit",
      "priority": 0.68,
      "search_score_v1": 0.68,
      "score_breakdown": {
        "expected_gain": 0.22,
        "implementation_risk": 0.24,
        "evidence_strength": 0.11,
        "code_reuse": 0.11
      },
      "predicted_gain_ms": 0.8,
      "predicted_fail_risk": 0.39,
      "ranking_notes": [
        "This is the cleanest kernel-variant swap that stays on the accepted row split.",
        "It ranks behind grouped-row tuning because the launch-order experiment is cheaper and more directly aligned with the scoreboard gap."
      ],
      "hypothesis": "The existing single-K 128x128 sibling keeps the accepted row split and one-K stage depth while changing the accumulate ordering away from the microkernel-specific path. That may trim scoreboard waste without paying the staged-128x128x32 cost.",
      "expected_bottleneck": "microkernel-specific accumulate ordering is contributing to scoreboard overhead on the accepted hot-band split",
      "code_locations": [
        "src/kernels/bf16_gemm_v1.cu:1839",
        "src/kernels/bf16_gemm_v1.cu:1924",
        "src/kernels/bf16_gemm_v1.cu:1956",
        "src/kernels/bf16_gemm_v1.cu:2114"
      ],
      "risk": "Moderate risk: the variant is in-tree, but it still lacks a clean measurement on the current baseline.",
      "metrics_to_recheck": [
        "median runtime",
        "launch__occupancy_limit_registers",
        "sm__warps_active.avg.pct_of_peak_sustained_active",
        "smsp__warp_issue_stalled_long_scoreboard_per_warp_active.pct"
      ],
      "stop_condition": "Stop if runtime regresses while register pressure and active-warps do not materially improve.",
      "evidence_refs": [
        "src/kernels/bf16_gemm_v1.cu",
        "runs/20260421_150626_bf16_gemm_v1_6cc462c4/ncu_analysis.md",
        "runs/20260421_150524_cublas_ref_clean_post_cleanup/ncu_analysis.md"
      ],
      "target_hotspots": [
        {
          "scope_type": "section",
          "scope_name": "Launch Statistics",
          "location": "Launch Statistics"
        }
      ],
      "expected_local_changes": [
        "Keep the accepted PTX hot-band row split.",
        "Swap the default hot-band launch from the PTX microkernel path to the existing single-K non-microkernel sibling."
      ],
      "guardrail_metrics": [
        {
          "metric_name": "launch__occupancy_limit_registers",
          "guardrail": "non_increasing"
        },
        {
          "metric_name": "smsp__warp_issue_stalled_long_scoreboard_per_warp_active.pct",
          "guardrail": "non_increasing"
        }
      ],
      "status": "open"
    },
    {
      "candidate_id": "diagnosis_20260421_150626_round01_clean_6cc462c4:dir_03",
      "source_diagnosis_id": "diagnosis_20260421_150626_round01_clean_6cc462c4",
      "base_run_id": "20260421_150626_bf16_gemm_v1_6cc462c4",
      "base_measured_commit": "6cc462c46b05712b972773911a1a7f31892ddcb2",
      "base_runtime_ms": 24.32352066,
      "direction_id": "dir_03",
      "direction_name": "Retune PTX Launch Bounds As A Fallback",
      "family_id": "register_pressure::retune_ptx_launch_bounds",
      "subfamily_id": "register_pressure::launch_bounds_128x128_ptx_min_blocks_2_to_3",
      "action_fingerprint": "clean_ptx_hotband_baseline:launch_bounds_min_blocks_2->3",
      "rank_in_diagnosis": 3,
      "recommended": false,
      "mode": "explore",
      "priority": 0.49,
      "search_score_v1": 0.49,
      "score_breakdown": {
        "expected_gain": 0.18,
        "implementation_risk": 0.33,
        "evidence_strength": 0.06,
        "code_reuse": 0.08
      },
      "predicted_gain_ms": 0.5,
      "predicted_fail_risk": 0.56,
      "ranking_notes": [
        "This remains worth keeping because the PTX path is still latency-limited.",
        "It ranks third because the clean cuBLAS profile does not suggest occupancy is the main missing lever."
      ],
      "hypothesis": "The clean PTX hotspot still sits at 200 registers per thread with occupancy capped at two blocks per SM. Tightening __launch_bounds__ may trim register pressure enough to improve latency hiding if the compiler does not spill.",
      "expected_bottleneck": "register pressure and low CTA residency on the accepted PTX hot-band path",
      "code_locations": [
        "src/kernels/bf16_gemm_v1.cu:1955"
      ],
      "risk": "High risk: forcing tighter launch bounds can introduce spills or a weaker schedule, and the cuBLAS reference does not point to occupancy as the main missing ingredient.",
      "metrics_to_recheck": [
        "median runtime",
        "launch__occupancy_limit_registers",
        "sm__warps_active.avg.pct_of_peak_sustained_active",
        "smsp__warp_issue_stalled_long_scoreboard_per_warp_active.pct"
      ],
      "stop_condition": "Stop immediately if build output or NCU shows spills, or if runtime regresses without reducing register pressure.",
      "evidence_refs": [
        "runs/20260421_150626_bf16_gemm_v1_6cc462c4/ncu_analysis.md",
        "runs/20260421_150524_cublas_ref_clean_post_cleanup/ncu_analysis.md",
        "src/kernels/bf16_gemm_v1.cu"
      ],
      "target_hotspots": [
        {
          "scope_type": "section",
          "scope_name": "Launch Statistics",
          "location": "Launch Statistics"
        },
        {
          "scope_type": "section",
          "scope_name": "Occupancy",
          "location": "Occupancy"
        }
      ],
      "expected_local_changes": [
        "Retune the PTX microkernel launch-bounds annotation and keep the rest of the launch topology unchanged for the first measurement."
      ],
      "guardrail_metrics": [
        {
          "metric_name": "launch__occupancy_limit_registers",
          "guardrail": "non_increasing"
        },
        {
          "metric_name": "sm__warps_active.avg.pct_of_peak_sustained_active",
          "guardrail": "non_decreasing"
        }
      ],
      "status": "open"
    }
  ],
  "notes": "Projected exactly three node_b directions into normalized search candidates."
}
